arvpyf/__init__.py
arvpyf/_version.py
arvpyf/ar.py
arvpyf/cf.py
arvpyf/mgmt.py
arvpyf/tests/__init__.py
arvpyf/tests/conftest.py
arvpyf/tests/test_ar.py
arvpyf/tests/cassettes/test_get
arvpyf-0.4.3.dist-info/AUTHORS.rst
arvpyf-0.4.3.dist-info/LICENSE
arvpyf-0.4.3.dist-info/METADATA
arvpyf-0.4.3.dist-info/WHEEL
arvpyf-0.4.3.dist-info/entry_points.txt
arvpyf-0.4.3.dist-info/top_level.txt
arvpyf-0.4.3.dist-info/RECORD
