Metadata-Version: 2.1
Name: arvpyf
Version: 0.4.3
Summary: Archiver Python Frontend
Home-page: https://github.com/NSLS-II/arvpyf
Author: Brookhaven National Lab
Author-email: DAMA@bnl.gov
License: BSD (3-clause)
Platform: UNKNOWN
Classifier: Development Status :: 2 - Pre-Alpha
Classifier: Natural Language :: English
Classifier: Programming Language :: Python :: 3
Requires-Dist: numpy
Requires-Dist: pandas
Requires-Dist: pytz
Requires-Dist: requests
